Metadata-Version: 2.4
Name: py-draughts
Version: 1.6.4
Summary: Fastest python draughts library with advanced WEB UI, move generation and validation, PDN and FEN parsing and writing and advenced engine + benchmarking. Supports multiple variants of game.
Author-email: Michał Skibiński <mskibinski109@gmail.com>
License:                     GNU GENERAL PUBLIC LICENSE
Project-URL: Homepage, https://github.com/michalskibinski109/py-draughts
Project-URL: Documentation, https://michalskibinski109.github.io/py-draughts/index.html
Project-URL: Repository, https://github.com/michalskibinski109/py-draughts
Keywords: draughts,checkers,AI,mini-max,game,board
Classifier: Development Status :: 5 - Production/Stable
Classifier: Intended Audience :: Developers
Classifier: Intended Audience :: Science/Research
Classifier: Operating System :: OS Independent
Classifier: Programming Language :: Python :: 3 :: Only
Classifier: Programming Language :: Python :: 3.9
Classifier: Programming Language :: Python :: 3.10
Classifier: Programming Language :: Python :: 3.11
Classifier: Programming Language :: Python :: 3.12
Classifier: Programming Language :: Python :: 3.13
Classifier: Programming Language :: Python :: 3.14
Classifier: Topic :: Games/Entertainment :: Board Games
Classifier: Topic :: Games/Entertainment :: Turn Based Strategy
Classifier: Topic :: Software Development :: Libraries :: Python Modules
Classifier: Typing :: Typed
Requires-Python: >=3.9
License-File: LICENSE
Requires-Dist: tqdm
Requires-Dist: numpy
Requires-Dist: loguru
Requires-Dist: fastapi
Requires-Dist: uvicorn
Requires-Dist: jinja2
Requires-Dist: httpx>=0.28.1
Requires-Dist: requests>=2.32.5
Provides-Extra: dev
Requires-Dist: pytest; extra == "dev"
Requires-Dist: mypy; extra == "dev"
Requires-Dist: sphinx; extra == "dev"
Requires-Dist: build; extra == "dev"
Requires-Dist: rich; extra == "dev"
Requires-Dist: pytest-benchmark; extra == "dev"
Dynamic: license-file
